orbit.py
setup.py
meteor_orbit.egg-info/PKG-INFO
meteor_orbit.egg-info/SOURCES.txt
meteor_orbit.egg-info/dependency_links.txt
meteor_orbit.egg-info/entry_points.txt
meteor_orbit.egg-info/not-zip-safe
meteor_orbit.egg-info/requires.txt
meteor_orbit.egg-info/top_level.txt