Metadata-Version: 1.0
Name: meteor-orbit
Version: 0.0.1
Summary: Virtual environment management for Meteor.js
Home-page: https://github.com/boundsj/orbit
Author: Jesse Bounds
Author-email: jesse@rebounds.net
License: MIT
Platform: any
Classifier: Development Status :: 4 - Beta
Classifier: Environment :: Web Environment
Classifier: Intended Audience :: Developers
Classifier: License :: OSI Approved :: MIT License
Classifier: Programming Language :: Python
Classifier: Topic :: Software Development :: Libraries :: Python Modules
